
{
    "games": [
      {
        "id": 1,
        "name": "Cyberpunk 2077",
        "description": "Cyberpunk 2077 is an open-world action-adventure RPG developed and published by CD Projekt Red, released on December 10, 2020. Set in the dystopian metropolis of Night City, the game is based on the Cyberpunk tabletop game series created by Mike Pondsmith. Players assume the role of V, a mercenary navigating a world of cyber-enhanced humans, corporate greed, and societal decay. The game’s narrative explores themes of identity, transhumanism, and the consequences of technological advancement.\n\nNight City is a sprawling urban environment divided into six distinct districts, each with its own culture, architecture, and challenges. Players can explore the city on foot or by vehicle, interacting with a variety of characters, factions, and gangs. The game features a branching storyline with multiple endings, shaped by the player’s choices and actions. These choices affect relationships, alliances, and the overall outcome of the story.\n\nCharacter customization is a key feature of Cyberpunk 2077. Players can customize V’s appearance, background, and skills, choosing from a variety of lifepaths that influence the story and dialogue options. The game’s RPG mechanics allow players to specialize in different playstyles, such as hacking, stealth, or combat. Cyberware enhancements, which replace or augment body parts, provide unique abilities and gameplay advantages.\n\nCombat in Cyberpunk 2077 is fast-paced and versatile, blending gunplay, melee combat, and hacking. Players can use a wide range of weapons, from firearms to melee weapons, and employ cybernetic abilities to gain an edge in battle. The hacking system, known as 'Quickhacking,' allows players to manipulate the environment, disable enemies, and gather information. The game also features a robust crafting system, enabling players to create and upgrade weapons, gear, and consumables.\n\nDespite its ambitious scope, Cyberpunk 2077 faced significant criticism at launch due to technical issues, particularly on last-generation consoles. However, CD Projekt Red has since released numerous patches and updates to improve performance and address bugs. The game’s narrative, world-building, and character development have been praised, with particular attention given to the performances of Keanu Reeves as Johnny Silverhand and Cherami Leigh as V.\n\nNight City itself is a visual marvel, with its neon-lit streets, towering skyscrapers, and gritty underbelly. The game’s art direction and attention to detail create an immersive and atmospheric world. The soundtrack, featuring a mix of original compositions and licensed tracks, enhances the game’s tone and setting.\n\nCyberpunk 2077 also includes a variety of side activities, such as gigs, cyberpsycho sightings, and street races, which provide additional context and depth to the world. The game’s expansion, 'Phantom Liberty,' introduces new story content, characters, and gameplay features, further enriching the experience.\n\nOverall, Cyberpunk 2077 is a bold and ambitious game that explores complex themes and offers a rich, immersive world. Despite its rocky launch, the game has garnered a dedicated fanbase and continues to evolve through updates and expansions.",
        "releaseDate": "2020-12-10",
        "officialSite": "https://www.cyberpunk.net",
        "imageUrl": "https://images.hdqwalls.com/download/game-cyberpunk-2077-4k-37-1920x1080.jpg"
      },
      {
        "id": 2,
        "name": "The Witcher 3",
        "description": "The Witcher 3: Wild Hunt is an open-world action role-playing game developed by CD Projekt Red and released on May 19, 2015. It is the third installment in The Witcher series, based on the book series by Andrzej Sapkowski. The game is set in a vast, rich fantasy world known as The Continent, where players assume the role of Geralt of Rivia, a professional monster hunter, or 'Witcher.' The game’s primary storyline follows Geralt's search for his adopted daughter, Ciri, who is being pursued by the mysterious Wild Hunt, a group of spectral riders. As Geralt, players also navigate political intrigue, complex moral choices, and deep character interactions, adding a layer of depth to the main quest.\n\nThe game features a large, open world with dynamic weather, a day-night cycle, and a variety of environments, including forests, villages, cities, and war-torn landscapes. Geralt can explore freely, interacting with NPCs, hunting monsters, and completing side quests that range from monster contracts to treasure hunts. The combat system combines fast-paced swordplay with magic, known as Signs, which include telekinetic force, fire, and defensive shields. Geralt can equip two swords: one for human enemies and one for monsters. Players can also craft items, brew potions, and use bombs, which adds layers of strategy to combat and exploration.\n\nOne of the standout features of The Witcher 3 is its narrative complexity. The game offers players a wealth of choices that influence the story and world around them. Many of these choices are morally ambiguous, forcing players to weigh their decisions carefully, knowing that they will have lasting consequences. Some decisions impact the fates of major characters, the political landscape, and even the environment. The game offers multiple endings based on the player’s choices, contributing to its replayability. The side content is equally rich, with numerous secondary quests that delve into the lives of different characters and provide further world-building. Additionally, players can engage in the card game Gwent, which became popular enough to have its own standalone spin-off.\n\nThe combat system in The Witcher 3 emphasizes both action and strategy. Geralt can utilize quick and strong attacks, dodging, and parrying to defeat enemies. Players are encouraged to study their opponents, using Geralt’s Witcher senses to gather information and exploit enemy weaknesses. The game’s RPG mechanics allow Geralt to level up, invest in different abilities, and improve his gear, which is essential to facing the increasingly difficult foes. Each monster type has its own strengths and weaknesses, and players must prepare accordingly, crafting potions or researching creatures to ensure success.\n\nThe visual quality of The Witcher 3 is often regarded as one of its defining features. The detailed environments, from dense forests to bustling cities, are brought to life with exceptional attention to detail. The art direction, along with the high-quality textures and dynamic weather, creates an immersive world that feels alive and vibrant. The game also features a standout soundtrack with an orchestral score that enhances the atmosphere and mood of each region. The voice acting, particularly Doug Cockle’s performance as Geralt, is highly praised and adds to the emotional weight of the story.\n\nThe Witcher 3 received universal acclaim upon release, with many considering it one of the greatest video games of all time. It won numerous Game of the Year awards and is praised for its deep storytelling, complex characters, and its massive, engaging world. The game’s impact on the RPG genre is profound, and it helped solidify CD Projekt Red’s reputation as a leading developer. The game’s success also led to a Netflix series adaptation, further expanding its reach and influence. Overall, The Witcher 3: Wild Hunt stands as a milestone in modern gaming, offering players an unforgettable, immersive experience filled with rich narrative, intricate gameplay, and a beautifully crafted world.",
        "releaseDate": "2015-05-19",
        "officialSite": "https://www.thewitcher.com",
        "imageUrl":"https://images.hdqwalls.com/wallpapers/the-witcher-3-game-hd-image.jpg"
      },
        {
            "id": 3,
            "name": "Doom Eternal",
            "description": "Doom Eternal is a first-person shooter developed by id Software and published by Bethesda Softworks, released on March 20, 2020. It is the fifth main installment in the Doom series and a direct sequel to the 2016 reboot of Doom. The game continues the story of the Doom Slayer, a legendary warrior who battles demonic forces from Hell to save humanity. Set on Earth and other dimensions, Doom Eternal expands on the fast-paced, brutal combat and intricate level design that defined its predecessor.\n\nThe gameplay of Doom Eternal emphasizes aggressive, high-speed combat. Players must constantly move, dodge, and attack to survive against hordes of demons. The game introduces new mechanics, such as the 'Flame Belch' for setting enemies on fire and harvesting armor, and the 'Blood Punch,' a powerful melee attack. The Doom Slayer’s arsenal includes iconic weapons like the Super Shotgun, Plasma Rifle, and BFG 9000, each with modifiable upgrades. Resource management is key, as players must chainsaw enemies for ammo, glory kill weakened foes for health, and use the Flame Belch for armor.\n\nDoom Eternal’s level design is more vertical and expansive than previous entries, encouraging exploration and platforming. The game features hidden collectibles, such as figurines, cheat codes, and lore entries, which provide additional context and rewards. The platforming sections, while divisive among players, add variety to the gameplay and showcase the game’s impressive environments.\n\nThe story of Doom Eternal delves deeper into the lore of the Doom universe, revealing the origins of the Doom Slayer and the conflict between Hell and the forces of Heaven. The game’s narrative is presented through environmental storytelling, cutscenes, and codex entries. While the focus remains on action, the expanded lore adds depth to the world and characters.\n\nVisually, Doom Eternal is a technical marvel, with highly detailed environments, fluid animations, and grotesque demon designs. The game’s art direction combines gothic and sci-fi elements, creating a unique and immersive aesthetic. The soundtrack, composed by Mick Gordon, features heavy metal and industrial music that complements the intense gameplay.\n\nDoom Eternal also includes a multiplayer mode called 'Battlemode,' where one player controls the Doom Slayer and two others control demons. This asymmetrical multiplayer mode offers a fresh take on the traditional deathmatch formula. Additionally, the game has received post-launch updates, including new campaign content and quality-of-life improvements.\n\nOverall, Doom Eternal is a masterclass in first-person shooter design, offering relentless action, deep mechanics, and a richly detailed world. It has been praised for its gameplay, visuals, and soundtrack, solidifying its place as one of the best shooters of its generation.",
            "releaseDate": "2020-03-20",
            "officialSite": "https://slayersclub.bethesda.net/en",
            "imageUrl": "https://wallpaperaccess.com/full/2631923.png"
        },
        {
            "id": 4,
            "name": "Hades",
            "description": "Hades is a roguelike action dungeon crawler developed and published by Supergiant Games, released on September 17, 2020. The game is set in the underworld of Greek mythology, where players control Zagreus, the son of Hades, as he attempts to escape his father’s domain and reach Mount Olympus. Each escape attempt is unique, with procedurally generated levels, enemies, and rewards.\n\nThe gameplay of Hades combines fast-paced combat with deep narrative elements. Players wield a variety of weapons, such as swords, bows, and shields, each with unique abilities and upgrades. As Zagreus progresses through the underworld, he gains boons from Olympian gods like Zeus, Athena, and Poseidon, which grant powerful abilities and modifiers. These boons can be combined in countless ways, allowing for diverse and customizable playstyles.\n\nHades’ roguelike structure ensures that no two runs are the same. While death sends Zagreus back to the House of Hades, players retain resources and story progress, encouraging repeated attempts. The game’s narrative unfolds gradually, with new dialogue, character interactions, and story revelations after each run. This approach keeps the story engaging and motivates players to continue playing.\n\nThe game’s art style is vibrant and detailed, with hand-drawn characters and environments that bring the underworld to life. The soundtrack, composed by Darren Korb, features a mix of rock, electronic, and orchestral music that complements the game’s tone and setting. The voice acting is also exceptional, with every character fully voiced and delivering memorable performances.\n\nHades has received widespread critical acclaim for its gameplay, narrative, and presentation. It won numerous Game of the Year awards and is considered one of the best roguelike games ever made. The game’s success has solidified Supergiant Games’ reputation as a leading indie developer.\n\nOverall, Hades is a masterful blend of action, storytelling, and replayability. Its engaging combat, rich narrative, and stunning visuals make it a must-play for fans of roguelikes and action games alike.",
            "releaseDate": "2020-09-17",
            "officialSite": "https://www.supergiantgames.com/games/hades",
            "imageUrl": "https://c4.wallpaperflare.com/wallpaper/556/514/424/hades-game-video-game-art-video-games-digital-art-artwork-hd-wallpaper-preview.jpg"
        },
        {
            "id": 5,
            "name": "Among Us",
            "description": "Among Us is a multiplayer social deduction game developed and published by InnerSloth, released on June 15, 2018. The game gained massive popularity in 2020, becoming a cultural phenomenon. Set in a space-themed environment, players are divided into two roles: Crewmates and Impostors. Crewmates must complete tasks around the map to win, while Impostors must sabotage the ship and eliminate Crewmates without being caught.\n\nThe gameplay of Among Us revolves around teamwork, deception, and strategy. Crewmates work together to complete tasks, such as fixing wiring, diverting power, and swiping cards, while Impostors try to blend in and eliminate them. Players can call emergency meetings to discuss suspicious behavior and vote to eject suspected Impostors. The game’s tension comes from the balance of trust and betrayal, as players must decide who to believe and who to eliminate.\n\nAmong Us supports 4 to 15 players, with the number of Impostors adjustable based on the group size. The game’s simple yet engaging mechanics make it accessible to players of all ages and skill levels. Its cartoonish art style and humorous animations add to its charm, making it a favorite for casual and competitive play alike.\n\nThe game’s popularity skyrocketed due to its suitability for streaming and online play, especially during the COVID-19 pandemic. Among Us became a staple of online content creation, with streamers and YouTubers creating countless videos and memes. The game’s social nature and emphasis on communication have made it a hit at parties and virtual gatherings.\n\nInnerSloth has continued to support Among Us with updates, including new maps, roles, and cosmetics. The game’s success has also led to plans for a sequel, though the original game remains widely played and beloved by its community.\n\nOverall, Among Us is a fun and engaging social deduction game that thrives on player interaction and strategy. Its simple mechanics, charming visuals, and emphasis on deception have made it one of the most popular multiplayer games of recent years.",
            "releaseDate": "2018-11-16",
            "officialSite": "https://innersloth.com/gameAmongUs.php",
            "imageUrl": "https://wallpapers.com/images/hd/among-us-space-background-l9i6kd6ax4uj7o0v.jpg"
        },
        {
            "id": 6,
            "name": "Valorant",
            "description": "Valorant is a free-to-play tactical first-person shooter developed and published by Riot Games, released on June 2, 2020. The game combines elements of tactical shooters like Counter-Strike: Global Offensive with hero-based shooters like Overwatch. Set in a near-future Earth, Valorant features two teams of five players competing in round-based matches. One team attacks while the other defends, with the goal of planting or defusing a spike (bomb) or eliminating the opposing team.\n\nEach player selects a character, known as an 'Agent,' each with unique abilities that complement different playstyles. Abilities include offensive skills, defensive tools, and utility options, such as smokes, flashes, and healing. Players must purchase weapons and abilities at the start of each round using in-game currency earned from previous rounds. This economic system adds a layer of strategy, as players must balance their spending to maximize their effectiveness.\n\nThe gameplay emphasizes precise gunplay, teamwork, and strategic use of abilities. Matches are fast-paced and require quick reflexes, map knowledge, and communication. Valorant’s maps are designed with multiple pathways, choke points, and bomb sites, encouraging diverse strategies and tactics. The game also features a ranking system, allowing players to compete in competitive matches and climb the ladder.\n\nValorant’s art style is clean and vibrant, with a focus on readability and performance. The game is optimized to run on a wide range of systems, making it accessible to a broad audience. The soundtrack and sound design are also noteworthy, with distinct audio cues for footsteps, abilities, and gunfire, which are crucial for gameplay.\n\nSince its release, Valorant has gained a massive following and has become a major title in the esports scene. Riot Games regularly updates the game with new Agents, maps, and balance changes to keep the meta fresh and engaging. The game’s competitive nature and low barrier to entry have made it a favorite among both casual and professional players.\n\nOverall, Valorant is a polished and strategic shooter that combines the best elements of tactical and hero-based gameplay. Its emphasis on skill, teamwork, and strategy has solidified its place as one of the most popular shooters in the world.",
            "releaseDate": "2020-06-02",
            "officialSite": "https://playvalorant.com",
            "imageUrl": "https://wallpaperaccess.com/full/3952295.jpg"
        },
        {
            "id": 7,
            "name": "Genshin Impact",
            "description": "Genshin Impact is an action role-playing game developed and published by miHoYo, now known as HoYoverse. Released on September 28, 2020, it is available on multiple platforms, including PlayStation 4, PlayStation 5, Microsoft Windows, Nintendo Switch, and mobile devices (iOS and Android). It is a free-to-play game, with in-game purchases available through a gacha system.\n\nThe game is set in the fantasy world of Teyvat, a land made up of seven distinct regions, each based on a different culture and element. The main storyline follows a mysterious character known as the Traveler, who is in search of their lost sibling. Players assume the role of the Traveler and explore the vast open world, unraveling mysteries and interacting with diverse characters along the way.\n\nGameplay in Genshin Impact revolves around exploration, combat, and puzzle-solving. The world is open-world and features a day-night cycle, dynamic weather, and expansive environments such as forests, mountains, and oceans. Players can glide through the skies, swim across bodies of water, and climb any surface, allowing for dynamic navigation.\n\nCombat is fast-paced and utilizes real-time action. Players can control a party of up to four characters, switching between them to execute combo attacks. Each character is associated with one of the seven elements: Anemo (Wind), Geo (Earth), Electro (Electric), Dendro (Nature), Hydro (Water), Pyro (Fire), and Cryo (Ice). Characters use their elemental powers to trigger elemental reactions such as vaporization, electro-charged, or melt, which adds layers of strategy to combat.\n\nThe gacha system allows players to summon new characters and weapons. This system is similar to a 'loot box,' where players spend Primogems, an in-game currency, to unlock new heroes and powerful gear. While the game is free to play, some aspects of the game require real money purchases, such as Primogems.\n\nIn addition to the story-driven content, Genshin Impact offers several side activities including dungeons, co-op multiplayer mode, timed challenges, and events that rotate regularly. Players can also improve their characters by collecting resources, leveling up, and upgrading gear.\n\nCharacters are central to the game's charm. Over time, more characters have been introduced, each with unique abilities, backstories, and personalities. The character design is heavily inspired by anime, and many players form attachments to their favorite characters. Some characters are available through story progression, while others are unlockable through the gacha system.\n\nThe soundtrack of Genshin Impact is highly praised for its orchestral compositions, with different pieces corresponding to the regions and themes of the game. The game’s world-building and lore are extensive, with each region containing deep mythology, factions, and storylines that players can explore.\n\nUpdates and Expansions: miHoYo regularly releases updates, adding new regions, characters, and events. Major content drops include the introduction of new story chapters, additional playable characters, and seasonal events. The game also frequently adds quality-of-life improvements based on player feedback.\n\nThe game’s multiplayer mode allows players to team up with up to three other people to explore the world and tackle challenges together. However, some elements of the game, such as the main story quests, are not available in multiplayer mode, focusing the co-op experience on exploration and side content.\n\nOverall, Genshin Impact is known for its breathtaking visuals, intricate gameplay mechanics, and expansive world. The game has garnered a massive global fanbase and has become one of the highest-grossing video games of all time, thanks to its engaging content and regular updates.",
            "releaseDate": "2020-09-28",
            "officialSite": "https://genshin.mihoyo.com",
            "imageUrl": "https://c4.wallpaperflare.com/wallpaper/883/1/94/anna-drw01-raiden-shogun-genshin-impact-hd-wallpaper-preview.jpg"
        },
    
        {
            "id": 8,
            "name": "Fortnite",
            "description": "Fortnite is a massively popular online multiplayer game developed by Epic Games, first released in 2017. The game is available on multiple platforms, including PC, PlayStation, Xbox, Nintendo Switch, and mobile devices. Fortnite is best known for its Battle Royale mode, where 100 players compete to be the last person or team standing. The game also features a creative mode, allowing players to build and share their own worlds, and a cooperative mode called 'Save the World,' where players fight against zombie-like creatures.\n\nIn Battle Royale mode, players are dropped onto an island and must scavenge for weapons, resources, and equipment while avoiding a shrinking storm that forces players into closer combat. The game’s building mechanic sets it apart from other battle royale games, allowing players to construct walls, ramps, and structures to gain a tactical advantage. This combination of shooting and building creates a unique and dynamic gameplay experience.\n\nFortnite’s art style is colorful and cartoonish, making it accessible to a wide audience. The game is free-to-play, with revenue generated through in-game purchases such as cosmetic items, battle passes, and emotes. These items do not affect gameplay but allow players to customize their characters and express themselves.\n\nThe game is constantly updated with new content, including seasonal events, limited-time modes, and collaborations with popular franchises such as Marvel, Star Wars, and Travis Scott. These updates keep the game fresh and engaging, contributing to its massive and dedicated player base.\n\nFortnite has also become a cultural phenomenon, with its dances and emotes becoming part of mainstream culture. The game has hosted virtual concerts and events, such as the Travis Scott Astronomical event, which attracted millions of players. Fortnite’s impact extends beyond gaming, influencing music, fashion, and entertainment.\n\nDespite its success, Fortnite has faced criticism for its addictive nature and the prevalence of microtransactions. However, its innovative gameplay, frequent updates, and cultural relevance have solidified its place as one of the most influential games of the modern era.",
            "releaseDate": "2017-07-25",
            "officialSite": "https://www.epicgames.com/fortnite",
            "imageUrl": "https://cdn.wallpapersafari.com/35/73/IpLAPC.png"
        },
        {
            "id": 9,
            "name": "League of Legends",
            "description": "League of Legends (LoL) is a multiplayer online battle arena (MOBA) game developed and published by Riot Games, released on October 27, 2009. The game has become one of the most popular and influential titles in the esports industry, with millions of players worldwide. In League of Legends, two teams of five players compete to destroy the opposing team’s Nexus, a structure located in their base, while defending their own.\n\nPlayers control characters known as 'Champions,' each with unique abilities and playstyles. Champions are divided into roles such as top laner, jungler, mid laner, bot laner (ADC), and support, each contributing to the team’s strategy. The game emphasizes teamwork, strategy, and skill, as players must work together to outmaneuver and outplay their opponents.\n\nLeague of Legends features a vast roster of over 150 Champions, with new ones added regularly. Each Champion has a distinct set of abilities, strengths, and weaknesses, allowing for diverse gameplay and strategies. Players can customize their Champions with runes, items, and skins, which are earned through gameplay or purchased with in-game currency.\n\nThe game is played on a map called Summoner’s Rift, which features three lanes, a jungle, and various objectives such as turrets, inhibitors, and neutral monsters like the Dragon and Baron Nashor. These objectives provide strategic advantages, such as buffs or map control, and are crucial to securing victory.\n\nLeague of Legends has a thriving esports scene, with professional leagues and tournaments held worldwide. The annual World Championship is one of the most-watched esports events, attracting millions of viewers and offering multi-million-dollar prize pools. The game’s competitive nature and deep mechanics have made it a staple of the esports community.\n\nRiot Games regularly updates League of Legends with balance changes, new Champions, and seasonal events to keep the game fresh and engaging. The game’s success has also led to spin-offs, such as Teamfight Tactics, Legends of Runeterra, and the animated series Arcane, which further expand the League of Legends universe.\n\nOverall, League of Legends is a landmark title in the gaming industry, known for its deep gameplay, vibrant community, and significant impact on esports. Its combination of strategy, skill, and teamwork has made it a favorite among players and spectators alike.",
            "releaseDate": "2009-10-27",   
            "officialSite": "https://na.leagueoflegends.com/en-us/",
            "imageUrl": "https://images8.alphacoders.com/406/406806.png"
        },
        {
            "id": 10,
            "name": "Minecraft",
            "description": "Minecraft is a sandbox video game developed by Mojang Studios, originally released on May 17, 2009. The game allows players to explore a blocky, procedurally generated 3D world, where they can gather resources, craft tools, build structures, and survive against various creatures. Minecraft is one of the best-selling video games of all time, with over 200 million copies sold and more than 140 million monthly active players as of 2023.\n\nThe game offers several modes, including Survival, Creative, Adventure, and Spectator. In Survival mode, players must gather resources, build shelters, and fend off enemies such as zombies, skeletons, and creepers. Creative mode gives players unlimited resources and the ability to fly, allowing for unrestricted building and exploration. Adventure mode is designed for custom maps and challenges, while Spectator mode allows players to observe the world without interacting with it.\n\nMinecraft’s open-ended gameplay encourages creativity and exploration. Players can build anything from simple houses to elaborate castles, cities, and even functional computers using the game’s redstone mechanics. The game’s world is virtually infinite, with diverse biomes such as forests, deserts, mountains, and oceans, each with unique resources and challenges.\n\nThe game also features a multiplayer mode, where players can collaborate on projects, compete in mini-games, or explore custom servers with unique rules and content. Minecraft’s modding community has created thousands of mods, texture packs, and custom maps, further expanding the game’s possibilities.\n\nMinecraft’s pixelated art style and simple mechanics have made it accessible to players of all ages. The game’s soundtrack, composed by C418, is iconic and adds to the game’s relaxing and immersive atmosphere. Over the years, Minecraft has received numerous updates, adding new features such as new biomes, mobs, blocks, and gameplay mechanics.\n\nIn addition to its entertainment value, Minecraft has been used in education to teach subjects like coding, history, and architecture. The game’s 'Education Edition' includes tools and resources specifically designed for classroom use.\n\nOverall, Minecraft is a cultural phenomenon that has left a lasting impact on the gaming industry. Its limitless creativity, engaging gameplay, and vibrant community have made it a beloved title for players around the world.",
            "releaseDate": "2011-11-18",
            "officialSite": "https://www.minecraft.net",
            "imageUrl": "https://images4.alphacoders.com/112/thumb-1920-1128578.jpg"
        },
        {
            "id": 11,
            "name": "World of Warcraft",
            "description": "World of Warcraft (WoW) is a massively multiplayer online role-playing game (MMORPG) developed and published by Blizzard Entertainment, released on November 23, 2004. Set in the high-fantasy world of Azeroth, the game is the fourth installment in the Warcraft series and has become one of the most influential and successful MMORPGs of all time. Players create characters from various races and classes, exploring the world, completing quests, and engaging in both player-versus-environment (PvE) and player-versus-player (PvP) content.\n\nThe game’s world is vast and immersive, featuring diverse zones, dungeons, and raids. Players can choose between two factions: the Alliance and the Horde, each with its own unique races and lore. The game’s narrative is driven by its rich lore, which includes epic storylines, memorable characters, and world-changing events. Expansions such as 'The Burning Crusade,' 'Wrath of the Lich King,' and 'Shadowlands' have continued to expand the game’s world and story.\n\nWorld of Warcraft’s gameplay revolves around questing, exploration, and combat. Players can level up their characters, acquire powerful gear, and customize their abilities through talent trees. The game features a variety of activities, including dungeons, raids, battlegrounds, and world events, catering to both casual and hardcore players.\n\nThe game’s social aspect is a key component of its success. Players can join guilds, form parties, and interact with others in a persistent online world. The game’s community is vibrant and active, with players collaborating on raids, trading items, and participating in role-playing events.\n\nWorld of Warcraft has had a significant impact on the gaming industry, popularizing the MMORPG genre and setting standards for online gaming. The game’s success has led to numerous spin-offs, including novels, comics, and the Warcraft movie. Blizzard Entertainment continues to support the game with regular updates, expansions, and events, ensuring its longevity and relevance.\n\nOverall, World of Warcraft is a landmark title in the gaming industry, known for its deep lore, engaging gameplay, and vibrant community. Its combination of exploration, storytelling, and social interaction has made it a favorite among millions of players worldwide.",
            "releaseDate": "2004-11-23",
            "officialSite": "https://worldofwarcraft.com",
            "imageUrl": "https://www.wallpaperflare.com/static/843/70/513/video-games-world-of-warcraft-illidan-stormrage-jaraxxus-wallpaper.jpg"
        },
        {
            "id": 12,
            "name": "Overwatch",
            "description": "Overwatch is a team-based multiplayer first-person shooter developed and published by Blizzard Entertainment, released on May 24, 2016. The game is set in a futuristic Earth and features a diverse cast of characters known as 'Heroes,' each with unique abilities and roles. Players work in teams of six to complete objectives such as capturing points, escorting payloads, or defending areas.\n\nThe gameplay of Overwatch emphasizes teamwork, strategy, and coordination. Heroes are divided into three roles: Damage, Tank, and Support. Damage heroes focus on dealing damage and eliminating enemies, Tank heroes absorb damage and protect their team, and Support heroes provide healing and utility. Players must work together to create effective team compositions and adapt to the evolving dynamics of each match.\n\nOverwatch’s vibrant art style and colorful characters have made it visually distinctive and appealing. The game’s lore is rich and expansive, with each Hero having a unique backstory and personality. Blizzard has expanded the game’s narrative through animated shorts, comics, and in-game events, creating a deep and engaging universe.\n\nThe game features a variety of modes, including Quick Play, Competitive Play, and Arcade. Competitive Play is the game’s ranked mode, where players can climb the ladder and earn rewards based on their performance. Arcade mode offers unique and rotating game types, such as Mystery Heroes and Deathmatch, providing a more casual and fun experience.\n\nOverwatch has been praised for its accessibility, depth, and inclusivity. The game’s diverse cast of characters and emphasis on teamwork have made it a favorite among players of all skill levels. The game’s success has also led to the creation of the Overwatch League, a professional esports league featuring teams from around the world.\n\nBlizzard has continued to support Overwatch with regular updates, including new Heroes, maps, and seasonal events. The game’s community is active and passionate, with players creating fan art, cosplay, and custom content.\n\nOverall, Overwatch is a landmark title in the first-person shooter genre, known for its engaging gameplay, vibrant visuals, and rich storytelling. Its emphasis on teamwork and strategy has made it a favorite among players and a staple of the esports scene.",
            "releaseDate": "2016-05-24",
            "officialSite": "https://playoverwatch.com",
            "imageUrl": "https://www.wallpaperflare.com/static/237/366/446/tracer-overwatch-hd-4k-wallpaper.jpg"
        },
        {
            "id": 13,
            "name": "Apex Legends",
            "description": "Apex Legends is a free-to-play battle royale-hero shooter game developed by Respawn Entertainment and published by Electronic Arts, released on February 4, 2019. The game is set in the Titanfall universe and features a unique blend of fast-paced combat, team-based gameplay, and character-driven mechanics. Players form squads of three and compete against other teams to be the last squad standing.\n\nThe gameplay of Apex Legends revolves around its diverse roster of 'Legends,' each with unique abilities and playstyles. Legends are divided into classes such as Offensive, Defensive, Support, and Recon, each contributing to the team’s strategy. Players must work together to outmaneuver and outplay their opponents, using their Legends’ abilities and the game’s advanced movement mechanics.\n\nApex Legends is known for its innovative features, such as the 'Ping System,' which allows players to communicate with their team without voice chat. The game also features a respawn mechanic, where eliminated teammates can be brought back into the match by retrieving their banner and using a respawn beacon. These features make the game more accessible and team-oriented.\n\nThe game’s maps are designed with verticality and diverse terrain, encouraging strategic positioning and movement. Players can slide, climb, and use ziplines to navigate the environment quickly. The game’s weapons and attachments are highly customizable, allowing players to adapt their loadouts to their playstyle.\n\nApex Legends has a vibrant and evolving narrative, with new Legends, maps, and storylines added regularly through seasonal updates. The game’s lore is expanded through in-game events, animated shorts, and comics, creating a rich and engaging universe.\n\nThe game’s success has led to a thriving esports scene, with tournaments and competitions held worldwide. Apex Legends’ fast-paced gameplay, strategic depth, and emphasis on teamwork have made it a favorite among both casual and competitive players.\n\nOverall, Apex Legends is a standout title in the battle royale genre, known for its innovative mechanics, diverse characters, and engaging gameplay. Its combination of fast-paced action and team-based strategy has made it one of the most popular shooters in recent years.",
            "releaseDate": "2019-02-04",
            "officialSite": "https://www.ea.com/games/apex-legends",
            "imageUrl": "https://images6.alphacoders.com/992/thumb-1920-992033.jpg"
        },
        {
            "id": 14,
            "name": "Call of Duty: Warzone",
            "description": "Call of Duty: Warzone is a free-to-play battle royale game developed by Infinity Ward and Raven Software, released on March 10, 2020. The game is part of the Call of Duty franchise and is integrated with Call of Duty: Modern Warfare (2019) and later Call of Duty: Black Ops Cold War. Warzone features two main modes: Battle Royale and Plunder, both set in the fictional city of Verdansk and later Caldera.\n\nIn Battle Royale mode, 150 players compete to be the last team or individual standing. Players can respawn by winning a 1v1 fight in the Gulag or by having teammates purchase redeploy tokens using in-game currency. The game introduces unique mechanics such as Contracts, which provide objectives like scavenging for loot or securing locations, and Loadout Drops, which allow players to customize their weapons and perks.\n\nPlunder mode focuses on collecting cash scattered across the map, with the goal of being the first team to reach a set amount or having the most cash when the timer runs out. This mode encourages aggressive gameplay and strategic decision-making.\n\nWarzone’s gameplay is fast-paced and emphasizes both gunplay and strategy. Players can use vehicles, deploy killstreaks, and utilize a variety of weapons and equipment to gain an advantage. The game’s map design, with its mix of urban areas, open spaces, and verticality, provides diverse combat scenarios and encourages tactical play.\n\nThe game is regularly updated with new content, including weapons, operators, and limited-time events. Warzone’s integration with other Call of Duty titles allows players to use weapons and operators from Modern Warfare and Black Ops Cold War, creating a unified experience.\n\nWarzone has become a major player in the battle royale genre, known for its polished gameplay, high production values, and active community. The game’s success has also led to a thriving esports scene, with tournaments and competitions held worldwide.\n\nOverall, Call of Duty: Warzone is a standout title in the battle royale genre, offering a blend of fast-paced action, strategic depth, and high-quality production. Its integration with the Call of Duty franchise and regular updates have made it a favorite among players and a staple of the gaming community.",
            "releaseDate": "2020-03-10",
            "officialSite": "https://www.callofduty.com/warzone",
            "imageUrl": "https://image-cdn.essentiallysports.com/wp-content/uploads/20200511140305/DrD.jpg"
         }

    ],
    "users": []
  }